README.rst
setup.py
jsonrpc_tornado/__init__.py
jsonrpc_tornado/jsonrpc.py
jsonrpc_tornado.egg-info/PKG-INFO
jsonrpc_tornado.egg-info/SOURCES.txt
jsonrpc_tornado.egg-info/dependency_links.txt
jsonrpc_tornado.egg-info/requires.txt
jsonrpc_tornado.egg-info/top_level.txt