Metadata-Version: 1.1
Name: jsonrpc-tornado
Version: 0.1.0
Summary: Asynchronous JSON-RPC client for Tornado
Home-page: https://github.com/artemmus/jsonrpc_tornado
Author: Artem Mustafa
Author-email: artemmus@yahoo.com
License: UNKNOWN
Keywords: json-rpc tornado asynchronous non-blocking
Platform: Any
Classifier: Development Status :: 3 - Alpha
Classifier: Environment :: Web Environment
Classifier: Intended Audience :: Developers
Classifier: License :: Freeware
Classifier: Operating System :: OS Independent
Classifier: Programming Language :: Python :: 2.7
Classifier: Programming Language :: Python :: 3
Classifier: Programming Language :: Python :: 3.4
Classifier: Topic :: Software Development :: Libraries :: Python Modules
Requires: tornado
